Metadata-Version: 1.1
Name: iqfeed
Version: 0.4.1
Summary: IQFeed / DTN Data downloader
Home-page: http://github.com/tibkiss/iqfeed
Author: Tibor Kiss
Author-email: tibor.kiss@gmail.com
License: Apache License, Version 2.0
Platform: UNKNOWN
Classifier: Development Status :: 4 - Beta
Classifier: License :: OSI Approved :: Apache Software License
Classifier: Programming Language :: Python :: 2.7
Classifier: Topic :: Office/Business :: Financial :: Investment
